revomonauto/__init__.py
revomonauto/data/__init__.py
revomonauto/data/gradex_clients/README.md
revomonauto/data/gradex_clients/__init__.py
revomonauto/data/gradex_clients/abilities_client/README.md
revomonauto/data/gradex_clients/abilities_client.py
revomonauto/data/gradex_clients/base_client.py
revomonauto/data/gradex_clients/battle_mechanics_client/README.md
revomonauto/data/gradex_clients/battle_mechanics_client.py
revomonauto/data/gradex_clients/capsules_client/README.md
revomonauto/data/gradex_clients/capsules_client.py
revomonauto/data/gradex_clients/counterdex_client/README.md
revomonauto/data/gradex_clients/counterdex_client.py
revomonauto/data/gradex_clients/evolution_client/README.md
revomonauto/data/gradex_clients/evolution_client.py
revomonauto/data/gradex_clients/fruitys_client/README.md
revomonauto/data/gradex_clients/fruitys_client.py
revomonauto/data/gradex_clients/items_client/README.md
revomonauto/data/gradex_clients/items_client.py
revomonauto/data/gradex_clients/locations_client/README.md
revomonauto/data/gradex_clients/locations_client.py
revomonauto/data/gradex_clients/moves_client/README.md
revomonauto/data/gradex_clients/moves_client.py
revomonauto/data/gradex_clients/natures_client/README.md
revomonauto/data/gradex_clients/natures_client.py
revomonauto/data/gradex_clients/owned_lands_client/README.md
revomonauto/data/gradex_clients/revomon_client/README.md
revomonauto/data/gradex_clients/revomon_client.py
revomonauto/data/gradex_clients/revomon_moves_client/README.md
revomonauto/data/gradex_clients/revomon_moves_client.py
revomonauto/data/gradex_clients/status_effects_client/README.md
revomonauto/data/gradex_clients/status_effects_client.py
revomonauto/data/gradex_clients/types_client/README.md
revomonauto/data/gradex_clients/types_client.py
revomonauto/data/gradex_clients/weather_client/README.md
revomonauto/data/gradex_clients/weather_client.py
revomonauto/data/gradex_jsons/abilities.json
revomonauto/data/gradex_jsons/capsules.json
revomonauto-0.7.0.dist-info/WHEEL
revomonauto-0.7.0.dist-info/METADATA
revomonauto-0.7.0.dist-info/RECORD
