Metadata-Version: 2.3
Name: revomonauto
Version: 0.7.0
Summary: Automation helpers for the Revomon Android game running under BlueStacks, built on top of the PymordialBlue automation framework.
Author: IAmNo1Special
Author-email: IAmNo1Special <ivmno1special@gmail.com>
Requires-Dist: pymordialblue>=0.1.1
Requires-Dist: requests>=2.32.5
Requires-Python: >=3.13
